enforcer_reloaded-1.0.1.data/scripts/reloaded
tests/__init__.py
tests/test_import.py
tests/test_secret.py
tests/chunks/__init__.py
tests/chunks/test_chunks.py
tests/interpolate/__init__.py
tests/interpolate/test_k8s_interpolate.py
tests/upload/__init__.py
tests/upload/test_secret_key_pattern.py
upside/__init__.py
upside/enforcer/__init__.py
upside/enforcer/app.py
upside/enforcer/config.py
upside/enforcer/interpolate/__init__.py
upside/enforcer/interpolate/cli.py
upside/enforcer/interpolate/k8s_schema.py
upside/enforcer/interpolate/util.py
upside/enforcer/ls/__init__.py
upside/enforcer/ls/cli.py
upside/enforcer/ls/util.py
upside/enforcer/show/__init__.py
upside/enforcer/show/cli.py
upside/enforcer/show/util.py
upside/enforcer/upload/__init__.py
upside/enforcer/upload/chunks.py
upside/enforcer/upload/cli.py
upside/enforcer/upload/util.py
upside/enforcer/util/__init__.py
upside/enforcer/util/auth.py
upside/enforcer/util/secret.py
upside/enforcer/util/tags.py
enforcer_reloaded-1.0.1.dist-info/AUTHORS.md
enforcer_reloaded-1.0.1.dist-info/LICENSE
enforcer_reloaded-1.0.1.dist-info/METADATA
enforcer_reloaded-1.0.1.dist-info/WHEEL
enforcer_reloaded-1.0.1.dist-info/top_level.txt
enforcer_reloaded-1.0.1.dist-info/RECORD
